Metadata-Version: 2.1
Name: ArukovicSonicMathility
Version: 0.0.1
Summary: Math module to make your life easier!
Home-page: UNKNOWN
Author: Arukovic
Author-email: preston20201976@gmail.com
License: MIT
Keywords: Math
Platform: UNKNOWN
Classifier: Development Status :: 5 - Production/Stable
Classifier: Intended Audience :: Education
Classifier: Operating System :: Microsoft :: Windows :: Windows 10
Classifier: License :: OSI Approved :: MIT License
Classifier: Programming Language :: Python :: 3
License-File: LICENCE.txt
